{"id":"main.js","dependencies":[],"generated":{"js":"$('.select').on('click', '.placeholder', function (e) {\n    var parent = $(this).closest('.select');\n    if (!parent.hasClass('is-open')) {\n        parent.addClass('is-open');\n        $('.select.is-open').not(parent).removeClass('is-open');\n    } else {\n        parent.removeClass('is-open');\n    }\n    e.stopPropagation();\n}).on('click', 'ul>li', function () {\n    var parent = $(this).closest('.select');\n    parent.removeClass('is-open').find('.placeholder').text($(this).text());\n});\n\n$('body').on('click', function () {\n    $('.select.is-open').removeClass('is-open');\n    console.log(\"js\");\n});\n//点击body关闭下拉框(BUG:body非常的小)","map":{"mappings":[{"name":"$","generated":{"line":1,"column":0},"source":"main.js","original":{"line":1,"column":0}},{"generated":{"line":1,"column":2},"source":"main.js","original":{"line":1,"column":2}},{"generated":{"line":1,"column":11},"source":"main.js","original":{"line":1,"column":0}},{"name":"on","generated":{"line":1,"column":13},"source":"main.js","original":{"line":1,"column":13}},{"generated":{"line":1,"column":15},"source":"main.js","original":{"line":1,"column":0}},{"generated":{"line":1,"column":16},"source":"main.js","original":{"line":1,"column":16}},{"generated":{"line":1,"column":23},"source":"main.js","original":{"line":1,"column":0}},{"generated":{"line":1,"column":25},"source":"main.js","original":{"line":1,"column":25}},{"generated":{"line":1,"column":39},"source":"main.js","original":{"line":1,"column":0}},{"generated":{"line":1,"column":41},"source":"main.js","original":{"line":1,"column":41}},{"name":"e","generated":{"line":1,"column":51},"source":"main.js","original":{"line":1,"column":50}},{"generated":{"line":1,"column":52},"source":"main.js","original":{"line":1,"column":41}},{"generated":{"line":1,"column":54},"source":"main.js","original":{"line":1,"column":53}},{"generated":{"line":2,"column":0},"source":"main.js","original":{"line":2,"column":4}},{"name":"parent","generated":{"line":2,"column":8},"source":"main.js","original":{"line":2,"column":8}},{"name":"$","generated":{"line":2,"column":17},"source":"main.js","original":{"line":2,"column":17}},{"generated":{"line":2,"column":19},"source":"main.js","original":{"line":2,"column":19}},{"generated":{"line":2,"column":23},"source":"main.js","original":{"line":2,"column":17}},{"name":"closest","generated":{"line":2,"column":25},"source":"main.js","original":{"line":2,"column":25}},{"generated":{"line":2,"column":32},"source":"main.js","original":{"line":2,"column":17}},{"generated":{"line":2,"column":33},"source":"main.js","original":{"line":2,"column":33}},{"generated":{"line":2,"column":42},"source":"main.js","original":{"line":2,"column":17}},{"generated":{"line":2,"column":43},"source":"main.js","original":{"line":2,"column":4}},{"generated":{"line":3,"column":0},"source":"main.js","original":{"line":3,"column":4}},{"generated":{"line":3,"column":8},"source":"main.js","original":{"line":3,"column":8}},{"name":"parent","generated":{"line":3,"column":9},"source":"main.js","original":{"line":3,"column":9}},{"name":"hasClass","generated":{"line":3,"column":16},"source":"main.js","original":{"line":3,"column":16}},{"generated":{"line":3,"column":24},"source":"main.js","original":{"line":3,"column":9}},{"generated":{"line":3,"column":25},"source":"main.js","original":{"line":3,"column":25}},{"generated":{"line":3,"column":34},"source":"main.js","original":{"line":3,"column":9}},{"generated":{"line":3,"column":35},"source":"main.js","original":{"line":3,"column":4}},{"generated":{"line":3,"column":37},"source":"main.js","original":{"line":3,"column":37}},{"name":"parent","generated":{"line":4,"column":0},"source":"main.js","original":{"line":4,"column":8}},{"name":"addClass","generated":{"line":4,"column":15},"source":"main.js","original":{"line":4,"column":15}},{"generated":{"line":4,"column":23},"source":"main.js","original":{"line":4,"column":8}},{"generated":{"line":4,"column":24},"source":"main.js","original":{"line":4,"column":24}},{"generated":{"line":4,"column":33},"source":"main.js","original":{"line":4,"column":8}},{"name":"$","generated":{"line":5,"column":0},"source":"main.js","original":{"line":5,"column":8}},{"generated":{"line":5,"column":10},"source":"main.js","original":{"line":5,"column":10}},{"generated":{"line":5,"column":27},"source":"main.js","original":{"line":5,"column":8}},{"name":"not","generated":{"line":5,"column":29},"source":"main.js","original":{"line":5,"column":29}},{"generated":{"line":5,"column":32},"source":"main.js","original":{"line":5,"column":8}},{"name":"parent","generated":{"line":5,"column":33},"source":"main.js","original":{"line":5,"column":33}},{"generated":{"line":5,"column":39},"source":"main.js","original":{"line":5,"column":8}},{"name":"removeClass","generated":{"line":5,"column":41},"source":"main.js","original":{"line":5,"column":41}},{"generated":{"line":5,"column":52},"source":"main.js","original":{"line":5,"column":8}},{"generated":{"line":5,"column":53},"source":"main.js","original":{"line":5,"column":53}},{"generated":{"line":5,"column":62},"source":"main.js","original":{"line":5,"column":8}},{"generated":{"line":6,"column":0},"source":"main.js","original":{"line":6,"column":5}},{"generated":{"line":6,"column":5},"source":"main.js","original":{"line":3,"column":4}},{"generated":{"line":6,"column":11},"source":"main.js","original":{"line":6,"column":11}},{"name":"parent","generated":{"line":7,"column":0},"source":"main.js","original":{"line":7,"column":8}},{"name":"removeClass","generated":{"line":7,"column":15},"source":"main.js","original":{"line":7,"column":15}},{"generated":{"line":7,"column":26},"source":"main.js","original":{"line":7,"column":8}},{"generated":{"line":7,"column":27},"source":"main.js","original":{"line":7,"column":27}},{"generated":{"line":7,"column":36},"source":"main.js","original":{"line":7,"column":8}},{"generated":{"line":8,"column":0},"source":"main.js","original":{"line":8,"column":5}},{"name":"e","generated":{"line":9,"column":0},"source":"main.js","original":{"line":9,"column":4}},{"name":"stopPropagation","generated":{"line":9,"column":6},"source":"main.js","original":{"line":9,"column":6}},{"generated":{"line":9,"column":21},"source":"main.js","original":{"line":9,"column":4}},{"generated":{"line":10,"column":0},"source":"main.js","original":{"line":10,"column":1}},{"generated":{"line":10,"column":1},"source":"main.js","original":{"line":1,"column":0}},{"name":"on","generated":{"line":10,"column":3},"source":"main.js","original":{"line":10,"column":3}},{"generated":{"line":10,"column":5},"source":"main.js","original":{"line":1,"column":0}},{"generated":{"line":10,"column":6},"source":"main.js","original":{"line":10,"column":6}},{"generated":{"line":10,"column":13},"source":"main.js","original":{"line":1,"column":0}},{"generated":{"line":10,"column":15},"source":"main.js","original":{"line":10,"column":15}},{"generated":{"line":10,"column":22},"source":"main.js","original":{"line":1,"column":0}},{"generated":{"line":10,"column":24},"source":"main.js","original":{"line":10,"column":24}},{"generated":{"line":10,"column":36},"source":"main.js","original":{"line":10,"column":35}},{"generated":{"line":11,"column":0},"source":"main.js","original":{"line":11,"column":4}},{"name":"parent","generated":{"line":11,"column":8},"source":"main.js","original":{"line":11,"column":8}},{"name":"$","generated":{"line":11,"column":17},"source":"main.js","original":{"line":11,"column":17}},{"generated":{"line":11,"column":19},"source":"main.js","original":{"line":11,"column":19}},{"generated":{"line":11,"column":23},"source":"main.js","original":{"line":11,"column":17}},{"name":"closest","generated":{"line":11,"column":25},"source":"main.js","original":{"line":11,"column":25}},{"generated":{"line":11,"column":32},"source":"main.js","original":{"line":11,"column":17}},{"generated":{"line":11,"column":33},"source":"main.js","original":{"line":11,"column":33}},{"generated":{"line":11,"column":42},"source":"main.js","original":{"line":11,"column":17}},{"generated":{"line":11,"column":43},"source":"main.js","original":{"line":11,"column":4}},{"name":"parent","generated":{"line":12,"column":0},"source":"main.js","original":{"line":12,"column":4}},{"name":"removeClass","generated":{"line":12,"column":11},"source":"main.js","original":{"line":12,"column":11}},{"generated":{"line":12,"column":22},"source":"main.js","original":{"line":12,"column":4}},{"generated":{"line":12,"column":23},"source":"main.js","original":{"line":12,"column":23}},{"generated":{"line":12,"column":32},"source":"main.js","original":{"line":12,"column":4}},{"name":"find","generated":{"line":12,"column":34},"source":"main.js","original":{"line":12,"column":34}},{"generated":{"line":12,"column":38},"source":"main.js","original":{"line":12,"column":4}},{"generated":{"line":12,"column":39},"source":"main.js","original":{"line":12,"column":39}},{"generated":{"line":12,"column":53},"source":"main.js","original":{"line":12,"column":4}},{"name":"text","generated":{"line":12,"column":55},"source":"main.js","original":{"line":12,"column":55}},{"generated":{"line":12,"column":59},"source":"main.js","original":{"line":12,"column":4}},{"name":"$","generated":{"line":12,"column":60},"source":"main.js","original":{"line":12,"column":60}},{"generated":{"line":12,"column":62},"source":"main.js","original":{"line":12,"column":62}},{"generated":{"line":12,"column":66},"source":"main.js","original":{"line":12,"column":60}},{"name":"text","generated":{"line":12,"column":68},"source":"main.js","original":{"line":12,"column":68}},{"generated":{"line":12,"column":72},"source":"main.js","original":{"line":12,"column":60}},{"generated":{"line":12,"column":74},"source":"main.js","original":{"line":12,"column":4}},{"generated":{"line":13,"column":0},"source":"main.js","original":{"line":13,"column":1}},{"generated":{"line":13,"column":1},"source":"main.js","original":{"line":1,"column":0}},{"name":"$","generated":{"line":15,"column":0},"source":"main.js","original":{"line":15,"column":0}},{"generated":{"line":15,"column":2},"source":"main.js","original":{"line":15,"column":2}},{"generated":{"line":15,"column":8},"source":"main.js","original":{"line":15,"column":0}},{"name":"on","generated":{"line":15,"column":10},"source":"main.js","original":{"line":15,"column":10}},{"generated":{"line":15,"column":12},"source":"main.js","original":{"line":15,"column":0}},{"generated":{"line":15,"column":13},"source":"main.js","original":{"line":15,"column":13}},{"generated":{"line":15,"column":20},"source":"main.js","original":{"line":15,"column":0}},{"generated":{"line":15,"column":22},"source":"main.js","original":{"line":15,"column":22}},{"generated":{"line":15,"column":34},"source":"main.js","original":{"line":15,"column":33}},{"name":"$","generated":{"line":16,"column":0},"source":"main.js","original":{"line":16,"column":4}},{"generated":{"line":16,"column":6},"source":"main.js","original":{"line":16,"column":6}},{"generated":{"line":16,"column":23},"source":"main.js","original":{"line":16,"column":4}},{"name":"removeClass","generated":{"line":16,"column":25},"source":"main.js","original":{"line":16,"column":25}},{"generated":{"line":16,"column":36},"source":"main.js","original":{"line":16,"column":4}},{"generated":{"line":16,"column":37},"source":"main.js","original":{"line":16,"column":37}},{"generated":{"line":16,"column":46},"source":"main.js","original":{"line":16,"column":4}},{"name":"console","generated":{"line":17,"column":0},"source":"main.js","original":{"line":17,"column":4}},{"name":"log","generated":{"line":17,"column":12},"source":"main.js","original":{"line":17,"column":12}},{"generated":{"line":17,"column":15},"source":"main.js","original":{"line":17,"column":4}},{"generated":{"line":17,"column":16},"source":"main.js","original":{"line":17,"column":16}},{"generated":{"line":17,"column":20},"source":"main.js","original":{"line":17,"column":4}},{"generated":{"line":18,"column":0},"source":"main.js","original":{"line":18,"column":1}},{"generated":{"line":18,"column":1},"source":"main.js","original":{"line":15,"column":0}},{"generated":{"line":19,"column":0},"source":"main.js","original":{"line":19,"column":0}}],"sources":{"main.js":"$('.select').on('click', '.placeholder', function(e) {\r\n    var parent = $(this).closest('.select');\r\n    if (!parent.hasClass('is-open')) {\r\n        parent.addClass('is-open');\r\n        $('.select.is-open').not(parent).removeClass('is-open');\r\n    } else {\r\n        parent.removeClass('is-open');\r\n    }\r\n    e.stopPropagation();\r\n}).on('click', 'ul>li', function() {\r\n    var parent = $(this).closest('.select');\r\n    parent.removeClass('is-open').find('.placeholder').text($(this).text());\r\n});\r\n \r\n$('body').on('click', function() {\r\n    $('.select.is-open').removeClass('is-open');\r\n    console.log(\"js\")\r\n});\r\n//点击body关闭下拉框(BUG:body非常的小)\r\n\r\n"},"lineCount":null}},"hash":"3e9dc2d665d5c3c65d6390b8fdb5d228","cacheData":{"env":{}}}